tgbot_logging/__init__.py
tgbot_logging/handler.py
tgbot_logging-1.0.2.dist-info/LICENSE
tgbot_logging-1.0.2.dist-info/METADATA
tgbot_logging-1.0.2.dist-info/WHEEL
tgbot_logging-1.0.2.dist-info/top_level.txt
tgbot_logging-1.0.2.dist-info/RECORD
