Metadata-Version: 2.1
Name: tgbot-logging
Version: 1.0.2
Summary: A Python logging handler that sends log messages to Telegram chats
Home-page: https://github.com/bykovk-pro/tgbot-logging
Author: Kirill Bykov
Author-email: me@bykovk.pro
Project-URL: Documentation, https://tgbot-logging.readthedocs.io/
Project-URL: Bug Reports, https://github.com/bykovk-pro/tgbot-logging/issues
Project-URL: Source Code, https://github.com/bykovk-pro/tgbot-logging
Keywords: telegram,logging,handler,async,batching,monitoring,notifications,chat,bot,signal,shutdown,graceful
Classifier: Development Status :: 5 - Production/Stable
Classifier: Intended Audience :: Developers
Classifier: License :: OSI Approved :: MIT License
Classifier: Operating System :: OS Independent
Classifier: Programming Language :: Python :: 3
Classifier: Programming Language :: Python :: 3.8
Classifier: Programming Language :: Python :: 3.9
Classifier: Programming Language :: Python :: 3.10
Classifier: Programming Language :: Python :: 3.11
Classifier: Topic :: System :: Logging
Classifier: Topic :: Communications :: Chat
Classifier: Framework :: AsyncIO
Classifier: Typing :: Typed
Requires-Python: >=3.8
License-File: LICENSE
Requires-Dist: python-telegram-bot>=20.0
Requires-Dist: python-dotenv>=0.19.0
Provides-Extra: dev
Requires-Dist: pytest>=7.0.0; extra == "dev"
Requires-Dist: pytest-asyncio>=0.20.0; extra == "dev"
Requires-Dist: pytest-cov>=4.0.0; extra == "dev"
Requires-Dist: black>=22.0.0; extra == "dev"
Requires-Dist: isort>=5.0.0; extra == "dev"
Requires-Dist: mypy>=0.990; extra == "dev"
Requires-Dist: bandit>=1.7.0; extra == "dev"
Requires-Dist: sphinx>=4.0.0; extra == "dev"
Requires-Dist: sphinx-rtd-theme>=1.0.0; extra == "dev"
